prynt3d/__init__.py
prynt3d/__main__.py
prynt3d/connector.py
prynt3d-1.0.0.dist-info/LICENSE
prynt3d-1.0.0.dist-info/METADATA
prynt3d-1.0.0.dist-info/WHEEL
prynt3d-1.0.0.dist-info/top_level.txt
prynt3d-1.0.0.dist-info/RECORD
